{
  "parent": "minecraft:block/block",
  "elements": [
    {
      "faces": {
        "down": {
          "texture": "#texture",
          "uv": [
            6.0,
            6.0,
            16.0,
            16.0
          ]
        },
        "east": {
          "texture": "#texture",
          "uv": [
            6.0,
            8.0,
            16.0,
            16.0
          ]
        },
        "north": {
          "texture": "#texture",
          "uv": [
            6.0,
            8.0,
            16.0,
            16.0
          ]
        },
        "south": {
          "texture": "#texture",
          "uv": [
            6.0,
            8.0,
            16.0,
            16.0
          ]
        },
        "up": {
          "texture": "#texture",
          "uv": [
            6.0,
            6.0,
            16.0,
            16.0
          ]
        },
        "west": {
          "texture": "#texture",
          "uv": [
            6.0,
            8.0,
            16.0,
            16.0
          ]
        }
      },
      "from": [
        6.0,
        8.0,
        6.0
      ],
      "to": [
        16.0,
        16.0,
        16.0
      ]
    }
  ],
  "textures": {
    "particle": "minecraft:block/warped_planks",
    "texture": "minecraft:block/warped_planks"
  }
}